odoo/addons/sale_timesheet_draft_invoice/README.rst
odoo/addons/sale_timesheet_draft_invoice/__init__.py
odoo/addons/sale_timesheet_draft_invoice/__manifest__.py
odoo/addons/sale_timesheet_draft_invoice/i18n/sale_timesheet_draft_invoice.pot
odoo/addons/sale_timesheet_draft_invoice/models/__init__.py
odoo/addons/sale_timesheet_draft_invoice/models/account_invoice.py
odoo/addons/sale_timesheet_draft_invoice/models/account_invoice_line.py
odoo/addons/sale_timesheet_draft_invoice/readme/CONTRIBUTORS.rst
odoo/addons/sale_timesheet_draft_invoice/readme/DESCRIPTION.rst
odoo/addons/sale_timesheet_draft_invoice/readme/ROADMAP.rst
odoo/addons/sale_timesheet_draft_invoice/static/description/icon.png
odoo/addons/sale_timesheet_draft_invoice/static/description/index.html
odoo/addons/sale_timesheet_draft_invoice/tests/__init__.py
odoo/addons/sale_timesheet_draft_invoice/tests/common.py
odoo/addons/sale_timesheet_draft_invoice/tests/test_invoice_lines.py
odoo11_addon_sale_timesheet_draft_invoice-11.0.1.0.0.99.dev4.dist-info/METADATA
odoo11_addon_sale_timesheet_draft_invoice-11.0.1.0.0.99.dev4.dist-info/WHEEL
odoo11_addon_sale_timesheet_draft_invoice-11.0.1.0.0.99.dev4.dist-info/top_level.txt
odoo11_addon_sale_timesheet_draft_invoice-11.0.1.0.0.99.dev4.dist-info/RECORD
